XMLCit/__init__.py
XMLCit/functions.py
XMLCit-0.0.9.dist-info/LICENSE
XMLCit-0.0.9.dist-info/METADATA
XMLCit-0.0.9.dist-info/WHEEL
XMLCit-0.0.9.dist-info/top_level.txt
XMLCit-0.0.9.dist-info/RECORD
