Metadata-Version: 2.1
Name: XMLCit
Version: 0.0.9
Summary: This package was made to edit XML files ( particularly TEI-XML files). The main purpose is to facilitate the tagging and edit of repeated citations and the inclusion of VIAF records
Home-page: https://github.com/hernandezj1/XMLCit
Author: Jose Hernandez
Author-email: jose.hndz.prz@gmail.com
Classifier: Programming Language :: Python :: 3
Classifier: License :: OSI Approved :: MIT License
Classifier: Operating System :: OS Independent
Requires-Python: >=3.6
License-File: LICENSE
